INSTALL.rst
LICENSE
MANIFEST.in
README.rst
VERSION
requirements.txt
setup.py
tasks.py
src/mbt/__init__.py
src/mbt/__main__.py
src/mbt/__meta__.py
src/mbt.egg-info/PKG-INFO
src/mbt.egg-info/SOURCES.txt
src/mbt.egg-info/dependency_links.txt
src/mbt.egg-info/not-zip-safe
src/mbt.egg-info/requires.txt
src/mbt.egg-info/top_level.txt
src/mbt/tests/__init__.py
src/mbt/tests/__main__.py
src/mbt/tests/test_documentation.py
src/mbt/tests/test_mbt.py